eazebot/__init__.py
eazebot/__main__.py
eazebot/auxiliary_methods.py
eazebot/bot.py
eazebot/handling.py
eazebot/main.py
eazebot/tradeHandler.py
eazebot/templates/APIs.json.tmp
eazebot/templates/botConfig.json.tmp
eazebot/templates/configureBot.bat.docker.tmp
eazebot/templates/configureBot.bat.python.tmp
eazebot/templates/startBot.bat.docker.tmp
eazebot/templates/startBot.bat.python.tmp
eazebot/templates/updateBot.bat.docker.tmp
eazebot/templates/updateBot.bat.python.tmp
eazebot-2.13.0.dist-info/DESCRIPTION.rst
eazebot-2.13.0.dist-info/METADATA
eazebot-2.13.0.dist-info/RECORD
eazebot-2.13.0.dist-info/WHEEL
eazebot-2.13.0.dist-info/metadata.json
eazebot-2.13.0.dist-info/top_level.txt
