Metadata-Version: 2.0
Name: eazebot
Version: 2.13.0
Summary: Free python/telegram bot for easy execution and surveillance of crypto trading plans on multiple exchanges
Home-page: https://github.com/marcelbeining/eazebot
Author: Marcel Beining
Author-email: marcel.beining@gmail.com
License: LGPLv3
Download-URL: https://github.com/marcelbeining/cryptotrader/archive/EazeBot_2.13.0.tar.gz
Requires-Dist: ccxt (==1.52.40)
Requires-Dist: python-dateutil (==2.8.1)
Requires-Dist: dill (==0.3.4)
Requires-Dist: numpy (==1.19.5)
Requires-Dist: requests (==2.25.1)
Requires-Dist: python-telegram-bot (==13.7)
Requires-Dist: dateparser (==1.0.0)
